census_utils/__init__.py
census_utils/_geocode.py
census_utils-0.0.6.dist-info/LICENSE
census_utils-0.0.6.dist-info/METADATA
census_utils-0.0.6.dist-info/WHEEL
census_utils-0.0.6.dist-info/top_level.txt
census_utils-0.0.6.dist-info/RECORD
