Metadata-Version: 2.1
Name: census-utils
Version: 0.0.6
Summary: your_description_here
Author-email: Cangyuan Li <everest229@gmail.com>
License: The MIT License (MIT)
Project-URL: Homepage, https://github.com/CangyuanLi/census_utils
Project-URL: Source, https://github.com/CangyuanLi/census_utils
Project-URL: Bug Reports, https://github.com/CangyuanLi/census_utils/issues
Classifier: Programming Language :: Python :: 3
Classifier: License :: OSI Approved :: MIT License
Requires-Python: >=3.7
License-File: LICENSE
Requires-Dist: polars
Requires-Dist: pandas
Requires-Dist: tqdm
